image_tagger/__init__.py
image_tagger/image_predictions.py
image_tagger/main.py
image_tagger/response_models.py
image_tagger-1.0.0.dist-info/LICENSE
image_tagger-1.0.0.dist-info/METADATA
image_tagger-1.0.0.dist-info/WHEEL
image_tagger-1.0.0.dist-info/top_level.txt
image_tagger-1.0.0.dist-info/RECORD
