Metadata-Version: 2.1
Name: image-tagger
Version: 1.0.0
Summary: A simple API for predicting ImageNet-1K labels of an image.
Home-page: https://github.com/dkarageo/image_tagger
Author: Dimitrios S. Karageorgiou
Author-email: soulrain@outlook.com
License: UNKNOWN
Project-URL: Bug Tracker, https://github.com/dkarageo/image_tagger/issues
Platform: UNKNOWN
Classifier: Programming Language :: Python :: 3
Classifier: License :: OSI Approved :: Mozilla Public License 2.0 (MPL 2.0)
Classifier: Operating System :: OS Independent
Classifier: Development Status :: 3 - Alpha
Requires-Python: >=3.9
License-File: LICENSE
Requires-Dist: tensorflow
Requires-Dist: Pillow
Requires-Dist: numpy
Requires-Dist: fastapi
Requires-Dist: uvicorn[standard]
Requires-Dist: pydantic
